{
  "type": "minecraft:entity",
  "pools": [
    {
      "bonus_rolls": 0,
      "conditions": [],
      "entries": [
        {
          "type": "minecraft:empty",
          "weight": 19
        },
        {
          "type": "minecraft:item",
          "name": "radik:disc_nosk",
          "weight": 1
        }
      ],
      "rolls": 1
    },
    {
      "rolls": 1,
      "entries": [
        {
          "type": "minecraft:tag",
          "name": "radik:froglights_item",
          "expand": false,
          "functions": [
            {
              "function": "minecraft:set_count",
              "count": {
                "min": 4,
                "max": 16
              },
              "add": true
            }
          ]
        }
      ]
    }
  ],
  "random_sequence": "minecraft:entities/ender_dragon"
}
